HISTORY.rst
LICENSE
MANIFEST.in
README.rst
setup.cfg
setup.py
src/streaming_pileupy.py
src/streaming_pileupy.egg-info/PKG-INFO
src/streaming_pileupy.egg-info/SOURCES.txt
src/streaming_pileupy.egg-info/dependency_links.txt
src/streaming_pileupy.egg-info/entry_points.txt
src/streaming_pileupy.egg-info/not-zip-safe
src/streaming_pileupy.egg-info/requires.txt
src/streaming_pileupy.egg-info/top_level.txt