Metadata-Version: 1.2
Name: streaming-pileupy
Version: 0.5.7
Summary: Create multi-sample text-pileups of streaming SAM/BAM files.
Home-page: https://github.com/winni2k/streaming_pileupy
Author: Warren W. Kretzschmar
Author-email: winni@warrenwk.com
License: MIT license
Keywords: streaming_pileupy
Platform: UNKNOWN
Classifier: Development Status :: 2 - Pre-Alpha
Classifier: Intended Audience :: Developers
Classifier: License :: OSI Approved :: MIT License
Classifier: Natural Language :: English
Classifier: Programming Language :: Python :: 3
Classifier: Programming Language :: Python :: 3.6
Classifier: Programming Language :: Python :: 3.7
Classifier: Programming Language :: Python :: 3.8
Requires-Python: >=3.6
